IpfsWeekly/README.md
IpfsWeekly/__init__.py
IpfsWeekly/__main__.py
IpfsWeekly/file.epub
IpfsWeekly/index.html
IpfsWeekly/css/__init__.py
IpfsWeekly/css/annotations.css
IpfsWeekly/css/main.css
IpfsWeekly/css/normalize.css
IpfsWeekly/css/popup.css
IpfsWeekly/font/__init__.py
IpfsWeekly/font/fontello.eot
IpfsWeekly/font/fontello.svg
IpfsWeekly/font/fontello.ttf
IpfsWeekly/font/fontello.woff
IpfsWeekly/img/__init__.py
IpfsWeekly/img/annotator-glyph-sprite.png
IpfsWeekly/img/annotator-icon-sprite.png
IpfsWeekly/img/apple-touch-icon.png
IpfsWeekly/img/cancelfullscreen.png
IpfsWeekly/img/close.png
IpfsWeekly/img/fullscreen.png
IpfsWeekly/img/loader.gif
IpfsWeekly/img/menu-icon.png
IpfsWeekly/img/save.png
IpfsWeekly/img/saved.png
IpfsWeekly/img/settings-s.png
IpfsWeekly/img/settings.png
IpfsWeekly/img/star.png
IpfsWeekly/js/__init__.py
IpfsWeekly/js/epub.js
IpfsWeekly/js/epub.min.js
IpfsWeekly/js/epub.min.map
IpfsWeekly/js/hooks.min.js
IpfsWeekly/js/hooks.min.map
IpfsWeekly/js/reader.js
IpfsWeekly/js/reader.js.map
IpfsWeekly/js/reader.min.js
IpfsWeekly/js/reader.min.map
IpfsWeekly/js/hooks/__init__.py
IpfsWeekly/js/hooks/extensions/__init__.py
IpfsWeekly/js/hooks/extensions/highlight.js
IpfsWeekly/js/libs/__init__.py
IpfsWeekly/js/libs/jquery.min.js
IpfsWeekly/js/libs/localforage.min.js
IpfsWeekly/js/libs/screenfull.js
IpfsWeekly/js/libs/screenfull.min.js
IpfsWeekly/js/libs/zip.min.js
IpfsWeekly/js/plugins/__init__.py
IpfsWeekly/js/plugins/hypothesis.js
IpfsWeekly/js/plugins/search.js
ipfs_weekly-2024.3.4.0.dist-info/METADATA
ipfs_weekly-2024.3.4.0.dist-info/WHEEL
ipfs_weekly-2024.3.4.0.dist-info/entry_points.txt
ipfs_weekly-2024.3.4.0.dist-info/top_level.txt
ipfs_weekly-2024.3.4.0.dist-info/RECORD
